README.md
setup.py
dogebuild_tex/__init__.py
dogebuild_tex/dogebuild_tex.version
dogebuild_tex/plugin.py
dogebuild_tex.egg-info/PKG-INFO
dogebuild_tex.egg-info/SOURCES.txt
dogebuild_tex.egg-info/dependency_links.txt
dogebuild_tex.egg-info/requires.txt
dogebuild_tex.egg-info/top_level.txt
dogebuild_tex/dogefile_internals/__init__.py