Metadata-Version: 2.1
Name: dogebuild-tex
Version: 0.1.3
Summary: Tex dogebuild plugin
Home-page: https://github.com/dogebuild/dogebuild-tex
Author: Kirill Sulim
Author-email: kirillsulim@gmail.com
License: mit
Keywords: dogebuild builder tex latex
Platform: UNKNOWN
Classifier: Development Status :: 2 - Pre-Alpha
Classifier: Environment :: Console
Classifier: Intended Audience :: Developers
Classifier: License :: OSI Approved :: MIT License
Classifier: Natural Language :: English
Classifier: Operating System :: OS Independent
Classifier: Topic :: Software Development
